tdimport_client/__init__.py
tdimport_client/models.py
tdimport_client/sftp_client.py
tdimport_client/tdimport_client.py
tdimport_client-0.2.4.dist-info/LICENSE.txt
tdimport_client-0.2.4.dist-info/METADATA
tdimport_client-0.2.4.dist-info/WHEEL
tdimport_client-0.2.4.dist-info/top_level.txt
tdimport_client-0.2.4.dist-info/RECORD
